README.rst
setup.py
memair/__init__.py
memair.egg-info/PKG-INFO
memair.egg-info/SOURCES.txt
memair.egg-info/dependency_links.txt
memair.egg-info/requires.txt
memair.egg-info/top_level.txt