Metadata-Version: 1.1
Name: memair
Version: 0.1
Summary: SDK for Memair
Home-page: https://github.com/memair/memair-python-sdk
Author: Greg Clarke
Author-email: greg@gho.st
License: MIT
Keywords: memair,quantified self,extended mind,lifelogging
Platform: UNKNOWN
Classifier: Development Status :: 4 - Beta
Classifier: Intended Audience :: Developers
Classifier: Topic :: Software Development :: Build Tools
Classifier: License :: OSI Approved :: MIT License
Classifier: Programming Language :: Python
